cacheunittest.py
cacheunittest-1.3.0.dist-info/LICENSE.txt
cacheunittest-1.3.0.dist-info/METADATA
cacheunittest-1.3.0.dist-info/WHEEL
cacheunittest-1.3.0.dist-info/top_level.txt
cacheunittest-1.3.0.dist-info/RECORD
