Metadata-Version: 2.1
Name: cacheunittest
Version: 1.3.0
Summary: Varnish integration unit test
Home-page: https://github.com/ArteGEIE/cache-unit-test
Author: Alapaje
Author-email: paje@github.com
License: LICENSE.txt
Platform: UNKNOWN
Requires-Python: >=3.7
License-File: LICENSE.txt
Requires-Dist: requests
